setup.py
digAgeRegexExtractor/__init__.py
digAgeRegexExtractor/age_regex_helper.py
digAgeRegexExtractor.egg-info/PKG-INFO
digAgeRegexExtractor.egg-info/SOURCES.txt
digAgeRegexExtractor.egg-info/dependency_links.txt
digAgeRegexExtractor.egg-info/requires.txt
digAgeRegexExtractor.egg-info/top_level.txt
test/__init__.py
test/test_age_extractor.py