Metadata-Version: 1.1
Name: digAgeRegexExtractor
Version: 0.3.0
Summary: digAgeRegexExtractor
Home-page: https://github.com/usc-isi-i2/dig-age-regex-extractor
Author: Jason Slepicka
Author-email: jasonslepicka@gmail.com
License: UNKNOWN
Download-URL: https://github.com/usc-isi-i2/dig-age-regex-extractor
Keywords: age,extractor
Platform: UNKNOWN
